{"directed": false, "multigraph": false, "graph": {}, "nodes": [{"degree": 2, "betweenness": 0.0, "eigenvector": 0.20810453499295894, "degree_cent": 0.18181818181818182, "modularity": 0, "id": "1893 Chicago World\u2019s Fair"}, {"degree": 6, "betweenness": 0.13636363636363635, "eigenvector": 0.4573865326234001, "degree_cent": 0.5454545454545454, "modularity": 0, "id": "1893 Chicago World's Fair"}, {"degree": 4, "betweenness": 0.0, "eigenvector": 0.37447149379602374, "degree_cent": 0.36363636363636365, "modularity": 0, "id": "ACA"}, {"degree": 4, "betweenness": 0.0, "eigenvector": 0.37447149379602374, "degree_cent": 0.36363636363636365, "modularity": 0, "id": "Home economics"}, {"degree": 4, "betweenness": 0.0, "eigenvector": 0.37447149379602374, "degree_cent": 0.36363636363636365, "modularity": 0, "id": "Naples Table Fellowship"}, {"degree": 7, "betweenness": 0.3242424242424242, "eigenvector": 0.4794469718904833, "degree_cent": 0.6363636363636364, "modularity": 0, "id": "New England Kitchen"}, {"degree": 4, "betweenness": 0.2303030303030303, "eigenvector": 0.24807130249968481, "degree_cent": 0.36363636363636365, "modularity": 1, "id": "cooking"}, {"degree": 2, "betweenness": 0.09696969696969696, "eigenvector": 0.12137015641391873, "degree_cent": 0.18181818181818182, "modularity": 0, "id": "Nutrition"}, {"degree": 3, "betweenness": 0.03636363636363636, "eigenvector": 0.06692768868426752, "degree_cent": 0.2727272727272727, "modularity": 1, "id": "nutrition"}, {"degree": 3, "betweenness": 0.01515151515151515, "eigenvector": 0.08995710903878007, "degree_cent": 0.2727272727272727, "modularity": 1, "id": "menus"}, {"degree": 3, "betweenness": 0.01515151515151515, "eigenvector": 0.08995710903878007, "degree_cent": 0.2727272727272727, "modularity": 1, "id": "progressive women"}, {"degree": 0, "betweenness": 0.0, "eigenvector": 1.9359965525543915e-20, "degree_cent": 0.0, "modularity": 1, "id": "source"}], "links": [{"weight": 0.7171371656006361, "source": "1893 Chicago World\u2019s Fair", "target": "1893 Chicago World's Fair"}, {"weight": 0.50709255283711, "source": "1893 Chicago World\u2019s Fair", "target": "New England Kitchen"}, {"weight": 0.5477225575051661, "source": "1893 Chicago World's Fair", "target": "ACA"}, {"weight": 0.5477225575051661, "source": "1893 Chicago World's Fair", "target": "Home economics"}, {"weight": 0.5477225575051661, "source": "1893 Chicago World's Fair", "target": "Naples Table Fellowship"}, {"weight": 0.565685424949238, "source": "1893 Chicago World's Fair", "target": "New England Kitchen"}, {"weight": 0.5477225575051661, "source": "1893 Chicago World's Fair", "target": "cooking"}, {"weight": 0.6666666666666666, "source": "ACA", "target": "Home economics"}, {"weight": 0.6666666666666666, "source": "ACA", "target": "Naples Table Fellowship"}, {"weight": 0.5163977794943222, "source": "ACA", "target": "New England Kitchen"}, {"weight": 0.6666666666666666, "source": "Home economics", "target": "Naples Table Fellowship"}, {"weight": 0.5163977794943222, "source": "Home economics", "target": "New England Kitchen"}, {"weight": 0.5163977794943222, "source": "Naples Table Fellowship", "target": "New England Kitchen"}, {"weight": 0.7191949522280763, "source": "New England Kitchen", "target": "Nutrition"}, {"weight": 0.5163977794943222, "source": "New England Kitchen", "target": "cooking"}, {"weight": 0.6666666666666666, "source": "cooking", "target": "menus"}, {"weight": 0.6666666666666666, "source": "cooking", "target": "progressive women"}, {"weight": 0.5803210823351056, "source": "Nutrition", "target": "nutrition"}, {"weight": 0.6660101754521279, "source": "nutrition", "target": "menus"}, {"weight": 0.6660101754521279, "source": "nutrition", "target": "progressive women"}, {"weight": 0.6666666666666666, "source": "menus", "target": "progressive women"}]}